{
  "id" : "https://RonanT8.github.io/IIIF_Project_M2TNAH/manifests/collection.json",
  "label" : {
    "en" : [ "All manifests loaded in RonanT8/IIIF_Project_M2TNAH project" ]
  },
  "type" : "Collection",
  "@context" : "http://iiif.io/api/presentation/3/context.json",
  "items" : [ {
    "@type" : "sc:Manifest",
    "@id" : "https://RonanT8.github.io/IIIF_Project_M2TNAH/manifests/manifest_iiif_project_representations_christ_evangelists.json",
    "label" : "[Click to edit label]"
  }, {
    "@type" : "sc:Manifest",
    "@id" : "https://RonanT8.github.io/IIIF_Project_M2TNAH/manifests/manifest_final.json",
    "label" : "Representing the Christ and the four living creatures in high medieval manuscripts"
  } ]
}